README.md
setup.py
nio/__init__.py
nio.egg-info/PKG-INFO
nio.egg-info/SOURCES.txt
nio.egg-info/dependency_links.txt
nio.egg-info/requires.txt
nio.egg-info/top_level.txt
nio/block/__init__.py
nio/block/base.py
nio/block/context.py
nio/block/generator_block.py
nio/block/terminals.py
nio/block/terminator_block.py
nio/block/mixins/__init__.py
nio/block/mixins/collector/__init__.py
nio/block/mixins/collector/collector.py
nio/block/mixins/enrich/__init__.py
nio/block/mixins/enrich/enrich_signals.py
nio/block/mixins/group_by/__init__.py
nio/block/mixins/group_by/group_by.py
nio/block/mixins/limit_lock/__init__.py
nio/block/mixins/limit_lock/limit_lock.py
nio/block/mixins/persistence/__init__.py
nio/block/mixins/persistence/persistence.py
nio/block/mixins/retry/__init__.py
nio/block/mixins/retry/retry.py
nio/block/mixins/retry/strategy.py
nio/block/mixins/retry/strategies/__init__.py
nio/block/mixins/retry/strategies/exponential.py
nio/block/mixins/retry/strategies/linear.py
nio/command/__init__.py
nio/command/base.py
nio/command/decorator.py
nio/command/holder.py
nio/command/params/__init__.py
nio/command/params/base.py
nio/command/params/dict.py
nio/command/params/float.py
nio/command/params/int.py
nio/command/params/list.py
nio/command/params/string.py
nio/modules/__init__.py
nio/modules/context.py
nio/modules/initializer.py
nio/modules/module.py
nio/modules/proxy.py
nio/modules/communication/__init__.py
nio/modules/communication/matching.py
nio/modules/communication/module.py
nio/modules/communication/publisher.py
nio/modules/communication/subscriber.py
nio/modules/communication/topic.py
nio/modules/persistence/__init__.py
nio/modules/persistence/module.py
nio/modules/persistence/persistence.py
nio/modules/scheduler/__init__.py
nio/modules/scheduler/job.py
nio/modules/scheduler/module.py
nio/modules/security/__init__.py
nio/modules/security/access.py
nio/modules/security/authenticator.py
nio/modules/security/authorizer.py
nio/modules/security/module.py
nio/modules/security/task.py
nio/modules/security/user.py
nio/modules/security/permissions/__init__.py
nio/modules/security/permissions/line.py
