Metadata-Version: 1.1
Name: nio
Version: 3.2.0
Summary: A framework for building blocks and modules for the nio Platform
Home-page: https://github.com/niolabs/nio
Author: niolabs
Author-email: support@n.io
License: Apache 2.0
Keywords: nio
Platform: UNKNOWN
Classifier: License :: OSI Approved :: Apache Software License
